examples/__init__.py
examples/basic.py
examples/email_classifier.py
examples/qa_chatbot.py
examples/semantic_search.py
examples/docs/__init__.py
examples/docs/big_n.py
examples/docs/emails.py
examples/docs/tech_docs.py
kiri/__init__.py
kiri/core.py
kiri/models/__init__.py
kiri/models/classification.py
kiri/models/custom_models.py
kiri/models/emotion.py
kiri/models/generation.py
kiri/models/generic_models.py
kiri/models/models.py
kiri/models/qa.py
kiri/models/summary.py
kiri/models/vectorisation.py
kiri/models/bart_large_mnli/__init__.py
kiri/models/bart_large_mnli/model.py
kiri/models/clip/__init__.py
kiri/models/clip/clip.py
kiri/models/clip/model.py
kiri/models/clip/module.py
kiri/models/clip/simple_tokenizer.py
kiri/models/distiluse_base_multilingual_cased_v2/__init__.py
kiri/models/distiluse_base_multilingual_cased_v2/model.py
kiri/models/gpt2_large/__init__.py
kiri/models/gpt2_large/model.py
kiri/models/msmarco_distilroberta_base_v2/__init__.py
kiri/models/msmarco_distilroberta_base_v2/model.py
kiri/models/t5/__init__.py
kiri/models/t5/model.py
kiri/models/t5_base_qa_summary_emotion/__init__.py
kiri/models/t5_base_qa_summary_emotion/model.py
kiri/models/tasks/__init__.py
kiri/models/tasks/base.py
kiri/models/tasks/classification.py
kiri/models/tasks/emotion.py
kiri/models/tasks/generation.py
kiri/models/tasks/image_classification.py
kiri/models/tasks/qa.py
kiri/models/tasks/summarisation.py
kiri/models/tasks/vectorisation.py
kiri/models/xlmr_large_xnli/__init__.py
kiri/models/xlmr_large_xnli/model.py
kiri/search/__init__.py
kiri/search/documents.py
kiri/search/search.py
kiri/tasks/__init__.py
kiri/tasks/base.py
kiri/tasks/emotion.py
kiri/tasks/image_classification.py
kiri/tasks/qa.py
kiri/tasks/summarisation.py
kiri/tasks/text_classification.py
kiri/tasks/text_generation.py
kiri/tasks/text_vectorisation.py
kiri/utils/__init__.py
kiri/utils/elastic.py
kiri/utils/load.py
kiri/utils/processing.py
kiri/utils/save.py
kiri/utils/upload.py
kiri/utils/verification.py
kiri-0.5.1.dist-info/LICENSE
kiri-0.5.1.dist-info/METADATA
kiri-0.5.1.dist-info/WHEEL
kiri-0.5.1.dist-info/top_level.txt
kiri-0.5.1.dist-info/RECORD
