Metadata-Version: 2.1
Name: kiri
Version: 0.5.1
Summary: Kiri
Home-page: https://github.com/kiri-ai/kiri
Author: Kiri OÜ
Author-email: hello@kiri.ai
License: UNKNOWN
Platform: UNKNOWN
Classifier: Programming Language :: Python :: 3
Classifier: License :: OSI Approved :: Apache Software License
Classifier: Operating System :: OS Independent
Requires-Python: >=3.6
Requires-Dist: dill
Requires-Dist: ftfy
Requires-Dist: pytorch-lightning (==1.1.0)
Requires-Dist: sentence-transformers (>=0.4.1.2)
Requires-Dist: torch
Requires-Dist: torchvision
Requires-Dist: transformers (>=4.3.2)
